README.md
setup.cfg
setup.py
populate_configs.egg-info/PKG-INFO
populate_configs.egg-info/SOURCES.txt
populate_configs.egg-info/dependency_links.txt
populate_configs.egg-info/entry_points.txt
populate_configs.egg-info/not-zip-safe
populate_configs.egg-info/requires.txt
populate_configs.egg-info/top_level.txt
populate_confs/__init__.py