Metadata-Version: 2.1
Name: populate-configs
Version: 0.0.5
Summary: Populate Jinja2 config files from yaml or json based config params
Home-page: https://github.com/GreenBuildingRegistry/populate-configs
Author: Fable Turas
Author-email: fable@rainsoftware.tech
Maintainer: GreenBuildingRegistry
Maintainer-email: admin@greenbuildingregistry.com
License: UNKNOWN
Keywords: config,yaml,jinja2
Platform: UNKNOWN
Classifier: Development Status :: 5 - Production/Stable
Classifier: Intended Audience :: Developers
Classifier: Operating System :: OS Independent
Classifier: Programming Language :: Python :: 3.5
Classifier: Programming Language :: Python :: 3.6
Classifier: Programming Language :: Python :: 3.7
Classifier: Programming Language :: Python :: 3.8
